[
    {
        "key": "dbln",
        "value": "%7B%22100072702724461%22%3A%222EdNP8pr%22%2C%2261568507944425%22%3A%22W3Lgq0zj%22%7D",
        "domain": "facebook.com",
        "path": "/login/device-based/",
        "hostOnly": false,
        "creation": "2025-04-17T04:42:22.139Z",
        "lastAccessed": "2025-04-17T04:42:22.140Z"
    },
    {
        "key": "datr",
        "value": "Y_fxZ9wMo5LGl6AlV1MhUDNJ",
        "domain": "facebook.com",
        "path": "/",
        "hostOnly": false,
        "creation": "2025-04-17T04:42:22.140Z",
        "lastAccessed": "2025-04-17T04:42:22.140Z"
    },
    {
        "key": "sb",
        "value": "Y_fxZ06oEd99do9rQRTg94HQ",
        "domain": "facebook.com",
        "path": "/",
        "hostOnly": false,
        "creation": "2025-04-17T04:42:22.140Z",
        "lastAccessed": "2025-04-17T04:42:22.140Z"
    },
    {
        "key": "ps_l",
        "value": "1",
        "domain": "facebook.com",
        "path": "/",
        "hostOnly": false,
        "creation": "2025-04-17T04:42:22.140Z",
        "lastAccessed": "2025-04-17T04:42:22.140Z"
    },
    {
        "key": "ps_n",
        "value": "1",
        "domain": "facebook.com",
        "path": "/",
        "hostOnly": false,
        "creation": "2025-04-17T04:42:22.140Z",
        "lastAccessed": "2025-04-17T04:42:22.140Z"
    },
    {
        "key": "m_pixel_ratio",
        "value": "2",
        "domain": "facebook.com",
        "path": "/",
        "hostOnly": false,
        "creation": "2025-04-17T04:42:22.140Z",
        "lastAccessed": "2025-04-17T04:42:22.140Z"
    },
    {
        "key": "vpd",
        "value": "v1%3B660x360x2",
        "domain": "facebook.com",
        "path": "/",
        "hostOnly": false,
        "creation": "2025-04-17T04:42:22.140Z",
        "lastAccessed": "2025-04-17T04:42:22.140Z"
    },
    {
        "key": "wd",
        "value": "360x376",
        "domain": "facebook.com",
        "path": "/",
        "hostOnly": false,
        "creation": "2025-04-17T04:42:22.140Z",
        "lastAccessed": "2025-04-17T04:42:22.140Z"
    },
    {
        "key": "c_user",
        "value": "61568507944425",
        "domain": "facebook.com",
        "path": "/",
        "hostOnly": false,
        "creation": "2025-04-17T04:42:22.140Z",
        "lastAccessed": "2025-04-17T04:42:22.140Z"
    },
    {
        "key": "fr",
        "value": "0IdXSU9Ed29WxiD5y.AWcrYUi-x0lkOC4Iij60MX2jSPc9i6IHw8IdsAYSKwe7s11FOcw.Bn8fdj..AAA.0.0.BoAIaD.AWfhalySYtajsDTHvwV2lqrJuZI",
        "domain": "facebook.com",
        "path": "/",
        "hostOnly": false,
        "creation": "2025-04-17T04:42:22.140Z",
        "lastAccessed": "2025-04-17T04:42:22.140Z"
    },
    {
        "key": "xs",
        "value": "18%3AcZWaQN7Xl-RoDQ%3A2%3A1744864899%3A-1%3A13882",
        "domain": "facebook.com",
        "path": "/",
        "hostOnly": false,
        "creation": "2025-04-17T04:42:22.140Z",
        "lastAccessed": "2025-04-17T04:42:22.140Z"
    },
    {
        "key": "locale",
        "value": "en_US",
        "domain": "facebook.com",
        "path": "/",
        "hostOnly": false,
        "creation": "2025-04-17T04:42:22.140Z",
        "lastAccessed": "2025-04-17T04:42:22.140Z"
    },
    {
        "key": "fbl_st",
        "value": "101634528%3BT%3A29081082",
        "domain": "facebook.com",
        "path": "/",
        "hostOnly": false,
        "creation": "2025-04-17T04:42:22.140Z",
        "lastAccessed": "2025-04-17T04:42:22.140Z"
    },
    {
        "key": "wl_cbv",
        "value": "v2%3Bclient_version%3A2790%3Btimestamp%3A1744864902%3BCRCM%3A-542981471",
        "domain": "facebook.com",
        "path": "/",
        "hostOnly": false,
        "creation": "2025-04-17T04:42:22.140Z",
        "lastAccessed": "2025-04-17T04:42:22.140Z"
    }
        ]
